stubber/__init__.py
stubber/board/board_info.csv
stubber/board/boot.py
stubber/board/createstubs.py
stubber/board/createstubs_db.py
stubber/board/createstubs_db_min.py
stubber/board/createstubs_db_mpy.mpy
stubber/board/createstubs_lvgl.py
stubber/board/createstubs_lvgl_min.py
stubber/board/createstubs_lvgl_mpy.mpy
stubber/board/createstubs_mem.py
stubber/board/createstubs_mem_min.py
stubber/board/createstubs_mem_mpy.mpy
stubber/board/createstubs_min.py
stubber/board/createstubs_mpy.mpy
stubber/board/fw_info.py
stubber/board/info.py
stubber/board/main.py
stubber/board/modulelist.txt
stubber/board/pkg_full.json
stubber/board/pkg_minified.json
stubber/board/pkg_mpy.json
stubber/board/pyrightconfig.json
stubber/bulk/mcu_stubber.py
stubber/codemod/__init__.py
stubber/codemod/_partials/__init__.py
stubber/codemod/_partials/db_main.py
stubber/codemod/_partials/lvgl_main.py
stubber/codemod/_partials/modules_reader.py
stubber/codemod/add_comment.py
stubber/codemod/add_method.py
stubber/codemod/board.py
stubber/codemod/enrich.py
stubber/codemod/merge_docstub.py
stubber/codemod/modify_list.py
stubber/codemod/utils.py
stubber/codemod/visitors/type_helpers.py
stubber/commands/__init__.py
stubber/commands/build_cmd.py
stubber/commands/cli.py
stubber/commands/clone_cmd.py
stubber/commands/config_cmd.py
stubber/commands/enrich_folder_cmd.py
stubber/commands/get_core_cmd.py
stubber/commands/get_docstubs_cmd.py
stubber/commands/get_frozen_cmd.py
stubber/commands/get_mcu_cmd.py
stubber/commands/merge_cmd.py
stubber/commands/publish_cmd.py
stubber/commands/stub_cmd.py
stubber/commands/switch_cmd.py
stubber/commands/variants_cmd.py
stubber/data/board_info.csv
stubber/data/board_info.json
stubber/data/micropython_tags.csv
stubber/data/requirements-core-micropython.txt
stubber/data/requirements-core-pycopy.txt
stubber/downloader.py
stubber/freeze/__init__.py
stubber/freeze/common.py
stubber/freeze/freeze_folder.py
stubber/freeze/freeze_manifest_2.py
stubber/freeze/get_frozen.py
micropython_stubber-1.26.3.dist-info/entry_points.txt
micropython_stubber-1.26.3.dist-info/LICENSE
micropython_stubber-1.26.3.dist-info/METADATA
micropython_stubber-1.26.3.dist-info/WHEEL
micropython_stubber-1.26.3.dist-info/RECORD
