Metadata-Version: 2.3
Name: micropython-stubber
Version: 1.26.3
Summary: Tooling to create and maintain stubs for MicroPython
License: MIT
Keywords: MicroPython,stubs,vscode,pyright,linting,static type check
Author: Jos Verlinde
Author-email: jos_verlinde@hotmail.com
Requires-Python: >=3.9.2,<4.0
Classifier: License :: OSI Approved :: MIT License
Classifier: Programming Language :: Python :: 3
Classifier: Programming Language :: Python :: 3.10
Classifier: Programming Language :: Python :: 3.11
Classifier: Programming Language :: Python :: 3.12
Classifier: Programming Language :: Python :: 3.13
Classifier: Programming Language :: Python :: Implementation :: CPython
Classifier: Programming Language :: Python :: Implementation :: MicroPython
Classifier: Topic :: Software Development :: Build Tools
Classifier: Topic :: Text Editors :: Integrated Development Environments (IDE)
Requires-Dist: autoflake (>=1.7,<3.0)
Requires-Dist: cachetools (>=5.3.0,<6.0.0)
Requires-Dist: click (>=8.1.3,<9.0.0)
Requires-Dist: executing (>=2.0.1,<3.0.0)
Requires-Dist: importlib-metadata (>=1,<9) ; python_version < "3.8"
Requires-Dist: libcst (>=1.1.0,<2.0.0)
Requires-Dist: loguru (>=0.6,<0.8)
Requires-Dist: mpflash (>=1.26.4,<2.0.0)
Requires-Dist: mpremote (>=1.25.0)
Requires-Dist: mpy-cross (>=1.25.0.post2,<2.0.0)
Requires-Dist: mypy (>=1.10)
Requires-Dist: mypy-gitlab-code-quality (>=1.1.0,<2.0.0)
Requires-Dist: packaging (>=24.2,<25.0)
Requires-Dist: pydeps (==3.0.1)
Requires-Dist: pygithub (>=2.1.1,<3.0.0)
Requires-Dist: pypi-simple (>=1.0.0,<2.0.0)
Requires-Dist: pyright (>=1.1.341)
Requires-Dist: pyserial (>=3.5)
Requires-Dist: python-minifier (>=2.7.0,<3.0.0) ; python_version < "3.14"
Requires-Dist: requests (>=2.32.3,<3.0.0)
Requires-Dist: rich-click (>=1.8.3,<2.0.0)
Requires-Dist: ruff (>=0.12.11,<0.13.0)
Requires-Dist: tenacity (==9.0.0)
Requires-Dist: tomli (>=2.0.1,<3.0.0) ; python_version < "3.11"
Requires-Dist: tomli-w (>=1.0.0,<2.0.0)
Requires-Dist: typed-config (>=1.3.0,<2.0.0)
Requires-Dist: urllib3 (>=2.2.2,<3.0.0)
Project-URL: Documentation, https://micropython-stubber.readthedocs.io/
Project-URL: Homepage, https://github.com/Josverl/micropython-stubber#readme
Project-URL: Repository, https://github.com/Josverl/micropython-stubber
